nbcommands/__init__.py
nbcommands/__version__.py
nbcommands/_black.py
nbcommands/_cat.py
nbcommands/_grep.py
nbcommands/_head.py
nbcommands/_less.py
nbcommands/_tail.py
nbcommands/_touch.py
nbcommands/terminal.py
nbcommands-0.5.1.dist-info/LICENSE
nbcommands-0.5.1.dist-info/METADATA
nbcommands-0.5.1.dist-info/WHEEL
nbcommands-0.5.1.dist-info/entry_points.txt
nbcommands-0.5.1.dist-info/top_level.txt
nbcommands-0.5.1.dist-info/RECORD
