Metadata-Version: 2.1
Name: nbcommands
Version: 0.5.1
Summary: Unix commands for Jupyter notebooks.
Home-page: https://github.com/vinayak-mehta/nbcommands
Author: Vinayak Mehta
Author-email: vmehta94@gmail.com
License: Apache 2.0
Platform: UNKNOWN
Classifier: License :: OSI Approved :: Apache Software License
Classifier: Programming Language :: Python :: 3.6
Classifier: Programming Language :: Python :: 3.7
Classifier: Programming Language :: Python :: 3.8
Classifier: Programming Language :: Python :: 3.9
Requires-Dist: black (>=19.10b0)
Requires-Dist: Click (>=7.0)
Requires-Dist: colorama (>=0.4.1)
Requires-Dist: nbformat (>=4.4.0)
Requires-Dist: Pygments (>=2.4.2)
Provides-Extra: dev
Requires-Dist: Sphinx (>=2.2.1) ; extra == 'dev'
Requires-Dist: black (>=19.10b0) ; extra == 'dev'
Requires-Dist: Click (>=7.0) ; extra == 'dev'
Requires-Dist: colorama (>=0.4.1) ; extra == 'dev'
Requires-Dist: nbformat (>=4.4.0) ; extra == 'dev'
Requires-Dist: Pygments (>=2.4.2) ; extra == 'dev'
